zeal_cli/__init__.py
zeal_cli/__main__.py
zeal_cli/zeal/__init__.py
zeal_cli/zeal/config.py
zeal_cli/zeal/docset.py
zeal_cli/zeal/downloads.py
zeal_cli/zeal/exceptions.py
zeal_cli/zeal/version.py
zeal_cli-2.0.0.dev3.dist-info/LICENSE
zeal_cli-2.0.0.dev3.dist-info/WHEEL
zeal_cli-2.0.0.dev3.dist-info/METADATA
zeal_cli-2.0.0.dev3.dist-info/entry_points.txt
zeal_cli-2.0.0.dev3.dist-info/RECORD
