Metadata-Version: 2.1
Name: zeal-cli
Version: 2.0.0.dev3
Summary: 
Home-page: https://github.com/morpheus636/zeal-cli
License: GPL-3.0-or-later
Author: Josh Levin
Author-email: morpheus636@morpheus636.com
Requires-Python: >=3.10,<3.11
Classifier: License :: OSI Approved :: GNU General Public License v3 or later (GPLv3+)
Classifier: Programming Language :: Python :: 3
Classifier: Programming Language :: Python :: 3.10
Requires-Dist: PyYAML (>=6.0,<7.0)
Requires-Dist: beautifulsoup4 (>=4.10.0,<5.0.0)
Requires-Dist: lxml (>=4.9.1,<5.0.0)
Requires-Dist: requests (>=2.27.1,<3.0.0)
Project-URL: Repository, https://github.com/morpheus636/zeal-cli
